MANIFEST.in
README.rst
setup.cfg
setup.py
before_after/__init__.py
before_after.egg-info/PKG-INFO
before_after.egg-info/SOURCES.txt
before_after.egg-info/dependency_links.txt
before_after.egg-info/entry_points.txt
before_after.egg-info/requires.txt
before_after.egg-info/top_level.txt
before_after/tests/__init__.py
before_after/tests/test_before_after.py
before_after/tests/test_functions.py