Metadata-Version: 1.1
Name: before-after
Version: 1.0.1
Summary: before_after provides utilities for testing race conditions
Home-page: https://github.com/c-oreills/before_after
Author: Christy O'Reilly
Author-email: christy@oreills.co.uk
License: GPLv2
Download-URL: https://github.com/c-oreills/before_after/tarball/1.0.1
Keywords: testing,race conditions
Platform: UNKNOWN
Classifier: Development Status :: 1 - Planning
Classifier: Natural Language :: English
Classifier: Operating System :: OS Independent
Classifier: Programming Language :: Python :: 2.7
